gv_proto/__init__.py
gv_proto/protobuf.py
gv_proto/grpcio/__init__.py
gv_proto/grpcio/interface_pb2_grpc.py
gv_proto/grpclib/__init__.py
gv_proto/grpclib/interface_grpc.py
gv_proto/proto/__init__.py
gv_proto/proto/archivist_pb2.py
gv_proto/proto/broadcaster_pb2.py
gv_proto/proto/common_pb2.py
gv_proto/proto/geographer_pb2.py
gv_proto/proto/interface_pb2.py
gv_service/__init__.py
gv_service/service.py
gv_utils/__init__.py
gv_utils/asyncio.py
gv_utils/csv.py
gv_utils/datetime.py
gv_utils/enums.py
gv_utils/filesystem.py
gv_utils/geometry.py
gv_utils/logger.py
gv_utils/multicpu.py
gv_vendor/__init__.py
gv_vendor/pylr/__init__.py
gv_vendor/pylr/binary.py
gv_vendor/pylr/constants.py
gv_vendor/pylr/decoder.py
gv_vendor/pylr/fow.py
gv_vendor/pylr/parser.py
gv_vendor/pylr/rating.py
gv_vendor/pylr/utils.py
gv_vendor/pylr/values.py
gv_vendor/pylr/version.py
gv_vendor/tomtom/ProtobufTrafficFlow_v5_pb2.py
gv_vendor/tomtom/__init__.py
gv_vendor/tomtom/gv_data_pb2.py
gtl_ville-2.1.51.dist-info/LICENSE.txt
gtl_ville-2.1.51.dist-info/METADATA
gtl_ville-2.1.51.dist-info/WHEEL
gtl_ville-2.1.51.dist-info/top_level.txt
gtl_ville-2.1.51.dist-info/RECORD
