Metadata-Version: 2.1
Name: gtl-ville
Version: 2.1.51
Summary: GTL Ville common packages
Home-page: https://gitlab.inria.fr/gtl-ville/gv-common
Author: Vadim BERTRAND
Author-email: vadim.bertrand@gipsa-lab.fr
License: MIT
Platform: UNKNOWN
Classifier: Development Status :: 4 - Beta
Classifier: Intended Audience :: Developers
Classifier: Topic :: Software Development
Classifier: License :: OSI Approved :: MIT License
Classifier: Programming Language :: Python
Classifier: Programming Language :: Python :: 3
Classifier: Programming Language :: Python :: 3.7
Classifier: Programming Language :: Python :: 3 :: Only
Requires-Python: >=3.7
Requires-Dist: aiofiles
Requires-Dist: asyncpg
Requires-Dist: grpcio-tools
Requires-Dist: grpclib (>=0.3.2rc1)
Requires-Dist: protobuf
Requires-Dist: python-dotenv
Requires-Dist: pytz
Requires-Dist: shapely
